[
  {
    "url": "https://spearfish.blackhills.bywatersolutions.com/cgi-bin/koha/opac-detail.pl?biblionumber=516100",
    "title": "The hybrid prince",
    "image_url": "https://images-na.ssl-images-amazon.com/images/P/1546129545.01.LZZZZZZZ.jpg",
    "record_type": "library_book",
    "source_label": "Grace Balloch Memorial Library"
  },
  {
    "url": "https://spearfish.blackhills.bywatersolutions.com/cgi-bin/koha/opac-detail.pl?biblionumber=515744",
    "title": "White River crossing",
    "image_url": "",
    "record_type": "library_book",
    "source_label": "Grace Balloch Memorial Library"
  },
  {
    "url": "https://spearfish.blackhills.bywatersolutions.com/cgi-bin/koha/opac-detail.pl?biblionumber=512038",
    "title": "The devil's daughter",
    "image_url": "https://images-na.ssl-images-amazon.com/images/P/0593498852.01.LZZZZZZZ.jpg",
    "record_type": "library_book",
    "source_label": "Grace Balloch Memorial Library"
  },
  {
    "url": "https://spearfish.blackhills.bywatersolutions.com/cgi-bin/koha/opac-detail.pl?biblionumber=520476",
    "title": "I'm so happy you're here",
    "image_url": "",
    "record_type": "library_book",
    "source_label": "Grace Balloch Memorial Library"
  },
  {
    "url": "https://spearfish.blackhills.bywatersolutions.com/cgi-bin/koha/opac-detail.pl?biblionumber=129943",
    "title": "The wall",
    "image_url": "https://images-na.ssl-images-amazon.com/images/P/0395515882.01.LZZZZZZZ.jpg",
    "record_type": "library_book",
    "source_label": "Grace Balloch Memorial Library"
  },
  {
    "url": "https://spearfish.blackhills.bywatersolutions.com/cgi-bin/koha/opac-detail.pl?biblionumber=514515",
    "title": "Jigsaw",
    "image_url": "https://images-na.ssl-images-amazon.com/images/P/0593497716.01.LZZZZZZZ.jpg",
    "record_type": "library_book",
    "source_label": "Grace Balloch Memorial Library"
  },
  {
    "url": "https://spearfish.blackhills.bywatersolutions.com/cgi-bin/koha/opac-detail.pl?biblionumber=308060",
    "title": "Little Excavator",
    "image_url": "https://images-na.ssl-images-amazon.com/images/P/1101999209.01.LZZZZZZZ.jpg",
    "record_type": "library_book",
    "source_label": "Grace Balloch Memorial Library"
  },
  {
    "url": "https://spearfish.blackhills.bywatersolutions.com/cgi-bin/koha/opac-detail.pl?biblionumber=152645",
    "title": "Stagecoach station 1, Dodge City",
    "image_url": "https://images-na.ssl-images-amazon.com/images/P/0816135533.01.LZZZZZZZ.jpg",
    "record_type": "library_book",
    "source_label": "Grace Balloch Memorial Library"
  },
  {
    "url": "https://spearfish.blackhills.bywatersolutions.com/cgi-bin/koha/opac-detail.pl?biblionumber=291518",
    "title": "Where hope prevails",
    "image_url": "https://images-na.ssl-images-amazon.com/images/P/0764217836.01.LZZZZZZZ.jpg",
    "record_type": "library_book",
    "source_label": "Grace Balloch Memorial Library"
  },
  {
    "url": "https://spearfish.blackhills.bywatersolutions.com/cgi-bin/koha/opac-detail.pl?biblionumber=57469",
    "title": "The dangerous days of Daniel X",
    "image_url": "https://images-na.ssl-images-amazon.com/images/P/0316002925.01.LZZZZZZZ.jpg",
    "record_type": "library_book",
    "source_label": "Grace Balloch Memorial Library"
  },
  {
    "url": "https://spearfish.blackhills.bywatersolutions.com/cgi-bin/koha/opac-detail.pl?biblionumber=160580",
    "title": "A voice in the wind",
    "image_url": "https://images-na.ssl-images-amazon.com/images/P/0842377506.01.LZZZZZZZ.jpg",
    "record_type": "library_book",
    "source_label": "Grace Balloch Memorial Library"
  },
  {
    "url": "https://spearfish.blackhills.bywatersolutions.com/cgi-bin/koha/opac-detail.pl?biblionumber=48085",
    "title": "The measure of a man",
    "image_url": "https://images-na.ssl-images-amazon.com/images/P/0061357901.01.LZZZZZZZ.jpg",
    "record_type": "library_book",
    "source_label": "Grace Balloch Memorial Library"
  },
  {
    "url": "https://spearfish.blackhills.bywatersolutions.com/cgi-bin/koha/opac-detail.pl?biblionumber=99785",
    "title": "Confessions of a sociopath",
    "image_url": "https://images-na.ssl-images-amazon.com/images/P/0307956644.01.LZZZZZZZ.jpg",
    "record_type": "library_book",
    "source_label": "Grace Balloch Memorial Library"
  },
  {
    "url": "https://spearfish.blackhills.bywatersolutions.com/cgi-bin/koha/opac-detail.pl?biblionumber=253090",
    "title": "Custer's Fall",
    "image_url": "https://images-na.ssl-images-amazon.com/images/P/0452010950.01.LZZZZZZZ.jpg",
    "record_type": "library_book",
    "source_label": "Grace Balloch Memorial Library"
  },
  {
    "url": "https://spearfish.blackhills.bywatersolutions.com/cgi-bin/koha/opac-detail.pl?biblionumber=291391",
    "title": "Curious minds",
    "image_url": "https://images-na.ssl-images-amazon.com/images/P/0553392689.01.LZZZZZZZ.jpg",
    "record_type": "library_book",
    "source_label": "Grace Balloch Memorial Library"
  },
  {
    "url": "https://spearfish.blackhills.bywatersolutions.com/cgi-bin/koha/opac-detail.pl?biblionumber=519478",
    "title": "Beyond a reasonable stout",
    "image_url": "https://images-na.ssl-images-amazon.com/images/P/1250766109.01.LZZZZZZZ.jpg",
    "record_type": "library_book",
    "source_label": "Grace Balloch Memorial Library"
  },
  {
    "url": "https://spearfish.blackhills.bywatersolutions.com/cgi-bin/koha/opac-detail.pl?biblionumber=163382",
    "title": "Traveling the Lewis & Clark Trail",
    "image_url": "https://images-na.ssl-images-amazon.com/images/P/1585920428.01.LZZZZZZZ.jpg",
    "record_type": "library_book",
    "source_label": "Grace Balloch Memorial Library"
  },
  {
    "url": "https://spearfish.blackhills.bywatersolutions.com/cgi-bin/koha/opac-detail.pl?biblionumber=399692",
    "title": "Ghost island",
    "image_url": "https://images-na.ssl-images-amazon.com/images/P/1534478663.01.LZZZZZZZ.jpg",
    "record_type": "library_book",
    "source_label": "Grace Balloch Memorial Library"
  },
  {
    "url": "https://spearfish.blackhills.bywatersolutions.com/cgi-bin/koha/opac-detail.pl?biblionumber=519496",
    "title": "Kingdom",
    "image_url": "https://images-na.ssl-images-amazon.com/images/P/1974761339.01.LZZZZZZZ.jpg",
    "record_type": "library_book",
    "source_label": "Grace Balloch Memorial Library"
  },
  {
    "url": "https://spearfish.blackhills.bywatersolutions.com/cgi-bin/koha/opac-detail.pl?biblionumber=373689",
    "title": "Pete the Kitty and the unicorn's missing colors",
    "image_url": "https://images-na.ssl-images-amazon.com/images/P/0062868462.01.LZZZZZZZ.jpg",
    "record_type": "library_book",
    "source_label": "Grace Balloch Memorial Library"
  },
  {
    "url": "https://spearfish.blackhills.bywatersolutions.com/cgi-bin/koha/opac-detail.pl?biblionumber=520383",
    "title": "Life in the great ice age",
    "image_url": "https://images-na.ssl-images-amazon.com/images/P/0890511675.01.LZZZZZZZ.jpg",
    "record_type": "library_book",
    "source_label": "Grace Balloch Memorial Library"
  },
  {
    "url": "https://spearfish.blackhills.bywatersolutions.com/cgi-bin/koha/opac-detail.pl?biblionumber=518313",
    "title": "Lady Tremaine",
    "image_url": "https://images-na.ssl-images-amazon.com/images/P/1250396344.01.LZZZZZZZ.jpg",
    "record_type": "library_book",
    "source_label": "Grace Balloch Memorial Library"
  },
  {
    "url": "https://spearfish.blackhills.bywatersolutions.com/cgi-bin/koha/opac-detail.pl?biblionumber=515404",
    "title": "At Morning's Light",
    "image_url": "https://images-na.ssl-images-amazon.com/images/P/1420533576.01.LZZZZZZZ.jpg",
    "record_type": "library_book",
    "source_label": "Grace Balloch Memorial Library"
  },
  {
    "url": "https://spearfish.blackhills.bywatersolutions.com/cgi-bin/koha/opac-detail.pl?biblionumber=518814",
    "title": "The rare bird",
    "image_url": "https://images-na.ssl-images-amazon.com/images/P/1250364396.01.LZZZZZZZ.jpg",
    "record_type": "library_book",
    "source_label": "Grace Balloch Memorial Library"
  },
  {
    "url": "https://spearfish.blackhills.bywatersolutions.com/cgi-bin/koha/opac-detail.pl?biblionumber=519681",
    "title": "An Amish widow's hope",
    "image_url": "https://images-na.ssl-images-amazon.com/images/P/1420533754.01.LZZZZZZZ.jpg",
    "record_type": "library_book",
    "source_label": "Grace Balloch Memorial Library"
  },
  {
    "url": "https://spearfish.blackhills.bywatersolutions.com/cgi-bin/koha/opac-detail.pl?biblionumber=519463",
    "title": "Son of nobody",
    "image_url": "https://images-na.ssl-images-amazon.com/images/P/132411813X.01.LZZZZZZZ.jpg",
    "record_type": "library_book",
    "source_label": "Grace Balloch Memorial Library"
  },
  {
    "url": "https://spearfish.blackhills.bywatersolutions.com/cgi-bin/koha/opac-detail.pl?biblionumber=520170",
    "title": "Final Victim.",
    "image_url": "https://images-na.ssl-images-amazon.com/images/P/1836183569.01.LZZZZZZZ.jpg",
    "record_type": "library_book",
    "source_label": "Grace Balloch Memorial Library"
  },
  {
    "url": "https://spearfish.blackhills.bywatersolutions.com/cgi-bin/koha/opac-detail.pl?biblionumber=519680",
    "title": "Plain Jane's secret admirer",
    "image_url": "https://images-na.ssl-images-amazon.com/images/P/1420533746.01.LZZZZZZZ.jpg",
    "record_type": "library_book",
    "source_label": "Grace Balloch Memorial Library"
  },
  {
    "url": "https://spearfish.blackhills.bywatersolutions.com/cgi-bin/koha/opac-detail.pl?biblionumber=516291",
    "title": "One bad mother",
    "image_url": "https://images-na.ssl-images-amazon.com/images/P/1668051117.01.LZZZZZZZ.jpg",
    "record_type": "library_book",
    "source_label": "Grace Balloch Memorial Library"
  },
  {
    "url": "https://spearfish.blackhills.bywatersolutions.com/cgi-bin/koha/opac-detail.pl?biblionumber=516680",
    "title": "The Astral Library",
    "image_url": "https://images-na.ssl-images-amazon.com/images/P/0063479753.01.LZZZZZZZ.jpg",
    "record_type": "library_book",
    "source_label": "Grace Balloch Memorial Library"
  },
  {
    "url": "https://spearfish.blackhills.bywatersolutions.com/cgi-bin/koha/opac-detail.pl?biblionumber=520369",
    "title": "The secrets of seabrook",
    "image_url": "https://spearfish.blackhills.bywatersolutions.com/cgi-bin/koha/opac-image.pl?biblionumber=520369",
    "record_type": "library_book",
    "source_label": "Grace Balloch Memorial Library"
  },
  {
    "url": "https://spearfish.blackhills.bywatersolutions.com/cgi-bin/koha/opac-detail.pl?biblionumber=495152",
    "title": "The butcher's masquerade",
    "image_url": "https://images-na.ssl-images-amazon.com/images/P/0593955994.01.LZZZZZZZ.jpg",
    "record_type": "library_book",
    "source_label": "Grace Balloch Memorial Library"
  },
  {
    "url": "https://spearfish.blackhills.bywatersolutions.com/cgi-bin/koha/opac-detail.pl?biblionumber=426332",
    "title": "My dear Hamilton",
    "image_url": "https://images-na.ssl-images-amazon.com/images/P/006246616X.01.LZZZZZZZ.jpg",
    "record_type": "library_book",
    "source_label": "Grace Balloch Memorial Library"
  },
  {
    "url": "https://spearfish.blackhills.bywatersolutions.com/cgi-bin/koha/opac-detail.pl?biblionumber=519679",
    "title": "Comancheria",
    "image_url": "https://images-na.ssl-images-amazon.com/images/P/1420533924.01.LZZZZZZZ.jpg",
    "record_type": "library_book",
    "source_label": "Grace Balloch Memorial Library"
  },
  {
    "url": "https://spearfish.blackhills.bywatersolutions.com/cgi-bin/koha/opac-detail.pl?biblionumber=493174",
    "title": "We do not part",
    "image_url": "https://images-na.ssl-images-amazon.com/images/P/0593595459.01.LZZZZZZZ.jpg",
    "record_type": "library_book",
    "source_label": "Grace Balloch Memorial Library"
  },
  {
    "url": "https://spearfish.blackhills.bywatersolutions.com/cgi-bin/koha/opac-detail.pl?biblionumber=519344",
    "title": "Faithful of Heart",
    "image_url": "https://images-na.ssl-images-amazon.com/images/P/1420533568.01.LZZZZZZZ.jpg",
    "record_type": "library_book",
    "source_label": "Grace Balloch Memorial Library"
  },
  {
    "url": "https://spearfish.blackhills.bywatersolutions.com/cgi-bin/koha/opac-detail.pl?biblionumber=514842",
    "title": "The hard line",
    "image_url": "https://images-na.ssl-images-amazon.com/images/P/0593954815.01.LZZZZZZZ.jpg",
    "record_type": "library_book",
    "source_label": "Grace Balloch Memorial Library"
  },
  {
    "url": "https://spearfish.blackhills.bywatersolutions.com/cgi-bin/koha/opac-detail.pl?biblionumber=519902",
    "title": "Go bananas!",
    "image_url": "https://images-na.ssl-images-amazon.com/images/P/166595356X.01.LZZZZZZZ.jpg",
    "record_type": "library_book",
    "source_label": "Grace Balloch Memorial Library"
  },
  {
    "url": "https://spearfish.blackhills.bywatersolutions.com/cgi-bin/koha/opac-detail.pl?biblionumber=482582",
    "title": "Dungeon crawler Carl",
    "image_url": "https://images-na.ssl-images-amazon.com/images/P/059382024X.01.LZZZZZZZ.jpg",
    "record_type": "library_book",
    "source_label": "Grace Balloch Memorial Library"
  },
  {
    "url": "https://spearfish.blackhills.bywatersolutions.com/cgi-bin/koha/opac-detail.pl?biblionumber=506862",
    "title": "The color of death",
    "image_url": "https://images-na.ssl-images-amazon.com/images/P/0063451913.01.LZZZZZZZ.jpg",
    "record_type": "library_book",
    "source_label": "Grace Balloch Memorial Library"
  },
  {
    "url": "https://spearfish.blackhills.bywatersolutions.com/cgi-bin/koha/opac-detail.pl?biblionumber=493255",
    "title": "The favorites",
    "image_url": "https://images-na.ssl-images-amazon.com/images/P/0593732049.01.LZZZZZZZ.jpg",
    "record_type": "library_book",
    "source_label": "Grace Balloch Memorial Library"
  },
  {
    "url": "https://spearfish.blackhills.bywatersolutions.com/cgi-bin/koha/opac-detail.pl?biblionumber=495150",
    "title": "The eye of the Bedlam Bride",
    "image_url": "https://images-na.ssl-images-amazon.com/images/P/059395601X.01.LZZZZZZZ.jpg",
    "record_type": "library_book",
    "source_label": "Grace Balloch Memorial Library"
  },
  {
    "url": "https://spearfish.blackhills.bywatersolutions.com/cgi-bin/koha/opac-detail.pl?biblionumber=517076",
    "title": "Wolf hour",
    "image_url": "",
    "record_type": "library_book",
    "source_label": "Grace Balloch Memorial Library"
  },
  {
    "url": "https://spearfish.blackhills.bywatersolutions.com/cgi-bin/koha/opac-detail.pl?biblionumber=93394",
    "title": "Goodnight, goodnight, construction site",
    "image_url": "https://images-na.ssl-images-amazon.com/images/P/0811877825.01.LZZZZZZZ.jpg",
    "record_type": "library_book",
    "source_label": "Grace Balloch Memorial Library"
  },
  {
    "url": "https://spearfish.blackhills.bywatersolutions.com/cgi-bin/koha/opac-detail.pl?biblionumber=486654",
    "title": "Kristy and the walking disaster",
    "image_url": "https://images-na.ssl-images-amazon.com/images/P/1338835564.01.LZZZZZZZ.jpg",
    "record_type": "library_book",
    "source_label": "Grace Balloch Memorial Library"
  },
  {
    "url": "https://spearfish.blackhills.bywatersolutions.com/cgi-bin/koha/opac-detail.pl?biblionumber=454184",
    "title": "The lost heir",
    "image_url": "https://images-na.ssl-images-amazon.com/images/P/0545942217.01.LZZZZZZZ.jpg",
    "record_type": "library_book",
    "source_label": "Grace Balloch Memorial Library"
  },
  {
    "url": "https://spearfish.blackhills.bywatersolutions.com/cgi-bin/koha/opac-detail.pl?biblionumber=336765",
    "title": "Kristy's big day",
    "image_url": "https://images-na.ssl-images-amazon.com/images/P/1338067680.01.LZZZZZZZ.jpg",
    "record_type": "library_book",
    "source_label": "Grace Balloch Memorial Library"
  },
  {
    "url": "https://spearfish.blackhills.bywatersolutions.com/cgi-bin/koha/opac-detail.pl?biblionumber=298407",
    "title": "Empire of storms",
    "image_url": "https://images-na.ssl-images-amazon.com/images/P/1619636077.01.LZZZZZZZ.jpg",
    "record_type": "library_book",
    "source_label": "Grace Balloch Memorial Library"
  },
  {
    "url": "https://spearfish.blackhills.bywatersolutions.com/cgi-bin/koha/opac-detail.pl?biblionumber=423059",
    "title": "Good-bye Stacey, good-bye",
    "image_url": "https://images-na.ssl-images-amazon.com/images/P/1338616056.01.LZZZZZZZ.jpg",
    "record_type": "library_book",
    "source_label": "Grace Balloch Memorial Library"
  },
  {
    "url": "https://spearfish.blackhills.bywatersolutions.com/cgi-bin/koha/opac-detail.pl?biblionumber=520454",
    "title": "Cops and Clobbers in Deadwood",
    "image_url": "",
    "record_type": "library_book",
    "source_label": "Grace Balloch Memorial Library"
  },
  {
    "url": "https://spearfish.blackhills.bywatersolutions.com/cgi-bin/koha/opac-detail.pl?biblionumber=371570",
    "title": "Camp Jupiter classified",
    "image_url": "https://images-na.ssl-images-amazon.com/images/P/136802405X.01.LZZZZZZZ.jpg",
    "record_type": "library_book",
    "source_label": "Grace Balloch Memorial Library"
  },
  {
    "url": "https://spearfish.blackhills.bywatersolutions.com/cgi-bin/koha/opac-detail.pl?biblionumber=487149",
    "title": "Escaping peril",
    "image_url": "https://images-na.ssl-images-amazon.com/images/P/1339001233.01.LZZZZZZZ.jpg",
    "record_type": "library_book",
    "source_label": "Grace Balloch Memorial Library"
  },
  {
    "url": "https://spearfish.blackhills.bywatersolutions.com/cgi-bin/koha/opac-detail.pl?biblionumber=376832",
    "title": "Wings of Fire",
    "image_url": "https://images-na.ssl-images-amazon.com/images/P/1338344226.01.LZZZZZZZ.jpg",
    "record_type": "library_book",
    "source_label": "Grace Balloch Memorial Library"
  },
  {
    "url": "https://spearfish.blackhills.bywatersolutions.com/cgi-bin/koha/opac-detail.pl?biblionumber=331160",
    "title": "Supernova",
    "image_url": "https://images-na.ssl-images-amazon.com/images/P/0545850029.01.LZZZZZZZ.jpg",
    "record_type": "library_book",
    "source_label": "Grace Balloch Memorial Library"
  },
  {
    "url": "https://spearfish.blackhills.bywatersolutions.com/cgi-bin/koha/opac-detail.pl?biblionumber=100259",
    "title": "Prince of the elves",
    "image_url": "https://images-na.ssl-images-amazon.com/images/P/0545208882.01.LZZZZZZZ.jpg",
    "record_type": "library_book",
    "source_label": "Grace Balloch Memorial Library"
  },
  {
    "url": "https://spearfish.blackhills.bywatersolutions.com/cgi-bin/koha/opac-detail.pl?biblionumber=84001",
    "title": "One Piece",
    "image_url": "https://images-na.ssl-images-amazon.com/images/P/1421515148.01.LZZZZZZZ.jpg",
    "record_type": "library_book",
    "source_label": "Grace Balloch Memorial Library"
  },
  {
    "url": "https://spearfish.blackhills.bywatersolutions.com/cgi-bin/koha/opac-detail.pl?biblionumber=461392",
    "title": "Claudia and the bad joke",
    "image_url": "https://images-na.ssl-images-amazon.com/images/P/1338835513.01.LZZZZZZZ.jpg",
    "record_type": "library_book",
    "source_label": "Grace Balloch Memorial Library"
  },
  {
    "url": "https://spearfish.blackhills.bywatersolutions.com/cgi-bin/koha/opac-detail.pl?biblionumber=400355",
    "title": "The paper palace",
    "image_url": "https://images-na.ssl-images-amazon.com/images/P/0593329821.01.LZZZZZZZ.jpg",
    "record_type": "library_book",
    "source_label": "Grace Balloch Memorial Library"
  },
  {
    "url": "https://spearfish.blackhills.bywatersolutions.com/cgi-bin/koha/opac-detail.pl?biblionumber=226855",
    "title": "Druids",
    "image_url": "https://images-na.ssl-images-amazon.com/images/P/0688088198.01.LZZZZZZZ.jpg",
    "record_type": "library_book",
    "source_label": "Grace Balloch Memorial Library"
  },
  {
    "url": "https://spearfish.blackhills.bywatersolutions.com/cgi-bin/koha/opac-detail.pl?biblionumber=198757",
    "title": "The bone labyrinth",
    "image_url": "https://images-na.ssl-images-amazon.com/images/P/0062381644.01.LZZZZZZZ.jpg",
    "record_type": "library_book",
    "source_label": "Grace Balloch Memorial Library"
  },
  {
    "url": "https://spearfish.blackhills.bywatersolutions.com/cgi-bin/koha/opac-detail.pl?biblionumber=339235",
    "title": "Hippie",
    "image_url": "https://images-na.ssl-images-amazon.com/images/P/0525655611.01.LZZZZZZZ.jpg",
    "record_type": "library_book",
    "source_label": "Grace Balloch Memorial Library"
  },
  {
    "url": "https://spearfish.blackhills.bywatersolutions.com/cgi-bin/koha/opac-detail.pl?biblionumber=226588",
    "title": "The tale of two bad mice",
    "image_url": "https://images-na.ssl-images-amazon.com/images/P/0723234647.01.LZZZZZZZ.jpg",
    "record_type": "library_book",
    "source_label": "Grace Balloch Memorial Library"
  },
  {
    "url": "https://spearfish.blackhills.bywatersolutions.com/cgi-bin/koha/opac-detail.pl?biblionumber=99408",
    "title": "The Final Cut",
    "image_url": "https://images-na.ssl-images-amazon.com/images/P/0399164731.01.LZZZZZZZ.jpg",
    "record_type": "library_book",
    "source_label": "Grace Balloch Memorial Library"
  },
  {
    "url": "https://spearfish.blackhills.bywatersolutions.com/cgi-bin/koha/opac-detail.pl?biblionumber=13226",
    "title": "Galilee",
    "image_url": "https://images-na.ssl-images-amazon.com/images/P/0060179473.01.LZZZZZZZ.jpg",
    "record_type": "library_book",
    "source_label": "Grace Balloch Memorial Library"
  },
  {
    "url": "https://spearfish.blackhills.bywatersolutions.com/cgi-bin/koha/opac-detail.pl?biblionumber=151882",
    "title": "Obsession",
    "image_url": "https://images-na.ssl-images-amazon.com/images/P/0345452631.01.LZZZZZZZ.jpg",
    "record_type": "library_book",
    "source_label": "Grace Balloch Memorial Library"
  },
  {
    "url": "https://spearfish.blackhills.bywatersolutions.com/cgi-bin/koha/opac-detail.pl?biblionumber=228140",
    "title": "Copper Hill",
    "image_url": "https://images-na.ssl-images-amazon.com/images/P/0786218053.01.LZZZZZZZ.jpg",
    "record_type": "library_book",
    "source_label": "Grace Balloch Memorial Library"
  },
  {
    "url": "https://spearfish.blackhills.bywatersolutions.com/cgi-bin/koha/opac-detail.pl?biblionumber=20829",
    "title": "Minnie and Moo Meet Frankenswine",
    "image_url": "https://images-na.ssl-images-amazon.com/images/P/0066237483.01.LZZZZZZZ.jpg",
    "record_type": "library_book",
    "source_label": "Grace Balloch Memorial Library"
  },
  {
    "url": "https://spearfish.blackhills.bywatersolutions.com/cgi-bin/koha/opac-detail.pl?biblionumber=228495",
    "title": "The Next Accident",
    "image_url": "https://images-na.ssl-images-amazon.com/images/P/0553802380.01.LZZZZZZZ.jpg",
    "record_type": "library_book",
    "source_label": "Grace Balloch Memorial Library"
  },
  {
    "url": "https://spearfish.blackhills.bywatersolutions.com/cgi-bin/koha/opac-detail.pl?biblionumber=298557",
    "title": "Mia and the too big tutu",
    "image_url": "https://images-na.ssl-images-amazon.com/images/P/0061733024.01.LZZZZZZZ.jpg",
    "record_type": "library_book",
    "source_label": "Grace Balloch Memorial Library"
  },
  {
    "url": "https://spearfish.blackhills.bywatersolutions.com/cgi-bin/koha/opac-detail.pl?biblionumber=152392",
    "title": "Carved in bone",
    "image_url": "https://images-na.ssl-images-amazon.com/images/P/006075981X.01.LZZZZZZZ.jpg",
    "record_type": "library_book",
    "source_label": "Grace Balloch Memorial Library"
  },
  {
    "url": "https://spearfish.blackhills.bywatersolutions.com/cgi-bin/koha/opac-detail.pl?biblionumber=227502",
    "title": "Grandfather's Trolley",
    "image_url": "https://images-na.ssl-images-amazon.com/images/P/1564026337.01.LZZZZZZZ.jpg",
    "record_type": "library_book",
    "source_label": "Grace Balloch Memorial Library"
  },
  {
    "url": "https://spearfish.blackhills.bywatersolutions.com/cgi-bin/koha/opac-detail.pl?biblionumber=100380",
    "title": "The day the crayons quit",
    "image_url": "https://images-na.ssl-images-amazon.com/images/P/0399255370.01.LZZZZZZZ.jpg",
    "record_type": "library_book",
    "source_label": "Grace Balloch Memorial Library"
  },
  {
    "url": "https://spearfish.blackhills.bywatersolutions.com/cgi-bin/koha/opac-detail.pl?biblionumber=379091",
    "title": "How do dinosaurs say happy birthday?",
    "image_url": "https://images-na.ssl-images-amazon.com/images/P/0545153530.01.LZZZZZZZ.jpg",
    "record_type": "library_book",
    "source_label": "Grace Balloch Memorial Library"
  },
  {
    "url": "https://spearfish.blackhills.bywatersolutions.com/cgi-bin/koha/opac-detail.pl?biblionumber=519628",
    "title": "Diamond Fever!: A True Crime Story in the Wild West.",
    "image_url": "https://images-na.ssl-images-amazon.com/images/P/1250265746.01.LZZZZZZZ.jpg",
    "record_type": "library_book",
    "source_label": "Grace Balloch Memorial Library"
  },
  {
    "url": "https://spearfish.blackhills.bywatersolutions.com/cgi-bin/koha/opac-detail.pl?biblionumber=519604",
    "title": "No way never sisters",
    "image_url": "https://images-na.ssl-images-amazon.com/images/P/1665974125.01.LZZZZZZZ.jpg",
    "record_type": "library_book",
    "source_label": "Grace Balloch Memorial Library"
  },
  {
    "url": "https://spearfish.blackhills.bywatersolutions.com/cgi-bin/koha/opac-detail.pl?biblionumber=516521",
    "title": "Pomona Afton Can Totally Catch a Killer",
    "image_url": "https://images-na.ssl-images-amazon.com/images/P/1668075687.01.LZZZZZZZ.jpg",
    "record_type": "library_book",
    "source_label": "Grace Balloch Memorial Library"
  },
  {
    "url": "https://spearfish.blackhills.bywatersolutions.com/cgi-bin/koha/opac-detail.pl?biblionumber=519622",
    "title": "Bug Ego, Vol. 1",
    "image_url": "https://images-na.ssl-images-amazon.com/images/P/1974762645.01.LZZZZZZZ.jpg",
    "record_type": "library_book",
    "source_label": "Grace Balloch Memorial Library"
  },
  {
    "url": "https://spearfish.blackhills.bywatersolutions.com/cgi-bin/koha/opac-detail.pl?biblionumber=520045",
    "title": "The neon sky",
    "image_url": "https://images-na.ssl-images-amazon.com/images/P/0316574988.01.LZZZZZZZ.jpg",
    "record_type": "library_book",
    "source_label": "Grace Balloch Memorial Library"
  },
  {
    "url": "https://spearfish.blackhills.bywatersolutions.com/cgi-bin/koha/opac-detail.pl?biblionumber=520512",
    "title": "Shrinking Violet",
    "image_url": "https://images-na.ssl-images-amazon.com/images/P/1797200720.01.LZZZZZZZ.jpg",
    "record_type": "library_book",
    "source_label": "Grace Balloch Memorial Library"
  },
  {
    "url": "https://spearfish.blackhills.bywatersolutions.com/cgi-bin/koha/opac-detail.pl?biblionumber=520507",
    "title": "Chasing shadows",
    "image_url": "https://images-na.ssl-images-amazon.com/images/P/006335716X.01.LZZZZZZZ.jpg",
    "record_type": "library_book",
    "source_label": "Grace Balloch Memorial Library"
  },
  {
    "url": "https://spearfish.blackhills.bywatersolutions.com/cgi-bin/koha/opac-detail.pl?biblionumber=476424",
    "title": "Pizza face",
    "image_url": "https://images-na.ssl-images-amazon.com/images/P/133857504X.01.LZZZZZZZ.jpg",
    "record_type": "library_book",
    "source_label": "Grace Balloch Memorial Library"
  },
  {
    "url": "https://spearfish.blackhills.bywatersolutions.com/cgi-bin/koha/opac-detail.pl?biblionumber=519154",
    "title": "Elizabeth Cady Stanton",
    "image_url": "https://images-na.ssl-images-amazon.com/images/P/1541647513.01.LZZZZZZZ.jpg",
    "record_type": "library_book",
    "source_label": "Grace Balloch Memorial Library"
  },
  {
    "url": "https://spearfish.blackhills.bywatersolutions.com/cgi-bin/koha/opac-detail.pl?biblionumber=492047",
    "title": "Diabetes cookbook & meal plan for the newly diagnosed",
    "image_url": "https://images-na.ssl-images-amazon.com/images/P/164152023X.01.LZZZZZZZ.jpg",
    "record_type": "library_book",
    "source_label": "Grace Balloch Memorial Library"
  },
  {
    "url": "https://spearfish.blackhills.bywatersolutions.com/cgi-bin/koha/opac-detail.pl?biblionumber=519810",
    "title": "Storey's guide to raising dairy goats",
    "image_url": "https://images-na.ssl-images-amazon.com/images/P/1603425802.01.LZZZZZZZ.jpg",
    "record_type": "library_book",
    "source_label": "Grace Balloch Memorial Library"
  },
  {
    "url": "https://spearfish.blackhills.bywatersolutions.com/cgi-bin/koha/opac-detail.pl?biblionumber=519471",
    "title": "Heir of illusion",
    "image_url": "https://images-na.ssl-images-amazon.com/images/P/1638934444.01.LZZZZZZZ.jpg",
    "record_type": "library_book",
    "source_label": "Grace Balloch Memorial Library"
  },
  {
    "url": "https://spearfish.blackhills.bywatersolutions.com/cgi-bin/koha/opac-detail.pl?biblionumber=520513",
    "title": "Honor flight",
    "image_url": "https://images-na.ssl-images-amazon.com/images/P/1536230154.01.LZZZZZZZ.jpg",
    "record_type": "library_book",
    "source_label": "Grace Balloch Memorial Library"
  },
  {
    "url": "https://spearfish.blackhills.bywatersolutions.com/cgi-bin/koha/opac-detail.pl?biblionumber=517909",
    "title": "The New Girl: First Crush: A Graphic Novel (the New Girl #2)",
    "image_url": "https://images-na.ssl-images-amazon.com/images/P/1338762494.01.LZZZZZZZ.jpg",
    "record_type": "library_book",
    "source_label": "Grace Balloch Memorial Library"
  }
]